adnipy/__init__.py
adnipy/adni.py
adnipy/adnipy.py
adnipy/data.py
adnipy-1.0.0.dist-info/licenses/AUTHORS.rst
adnipy-1.0.0.dist-info/licenses/LICENSE
adnipy-1.0.0.dist-info/METADATA
adnipy-1.0.0.dist-info/WHEEL
adnipy-1.0.0.dist-info/top_level.txt
adnipy-1.0.0.dist-info/RECORD
