Metadata-Version: 2.4
Name: adnipy
Version: 1.0.0
Summary: Process ADNI study data with adnipy.
Home-page: https://github.com/mcsitter/adnipy
Author: Maximilian Cosmo Sitter
Author-email: Maximilian Cosmo Sitter <msitter@smail.uni-koeln.de>
License: MIT License
Project-URL: Homepage, https://github.com/mcsitter/adnipy
Keywords: adnipy
Platform: any
Classifier: Development Status :: 1 - Planning
Classifier: Intended Audience :: Science/Research
Classifier: License :: OSI Approved :: MIT License
Classifier: Natural Language :: English
Classifier: Operating System :: OS Independent
Classifier: Programming Language :: Python :: 3.10
Classifier: Programming Language :: Python :: 3.11
Classifier: Programming Language :: Python :: 3.12
Classifier: Programming Language :: Python :: 3.13
Requires-Python: >=3.8.0
License-File: LICENSE
License-File: AUTHORS.rst
Requires-Dist: pandas>=2.0.0
Requires-Dist: matplotlib>=3.0.0
Dynamic: author
Dynamic: home-page
Dynamic: license-file
Dynamic: platform
Dynamic: requires-python
